{"a": "3", "b": "5", "c": "b", "d": "H", "e": "R", "f": "p", "g": "m", "h": "q", "i": "Y", "j": "J", "k": "k", "l": "V", "m": "M", "n": "N", "o": "L", "p": "v", "q": "y", "r": " ", "s": "U", "t": "P", "u": "x", "v": "o", "w": "1", "x": "w", "y": "c", "z": "W", "A": "9", "B": "F", "C": "a", "D": "Z", "E": "B", "F": "j", "G": "4", "H": "e", "I": "h", "J": "r", "K": "8", "L": "I", "M": "n", "N": ",", "O": ".", "P": "l", "Q": "g", "R": "Q", "S": "E", "T": "A", "U": "t", "V": "G", "W": "u", "X": "7", "Y": "K", "Z": "2", "1": "S", "2": "i", "3": "C", "4": "O", "5": "d", "6": "T", "7": "6", "8": "s", "9": "D", "'": "'", ".": "X", ",": "f", " ": "z"}